README.txt
setup.py
ryoka_utils/__init__.py
ryoka_utils/debugger.py
ryoka_utils/mail.py
ryoka_utils/slack.py
ryoka_utils/test.py
ryoka_utils/utils.py
ryoka_utils.egg-info/PKG-INFO
ryoka_utils.egg-info/SOURCES.txt
ryoka_utils.egg-info/dependency_links.txt
ryoka_utils.egg-info/requires.txt
ryoka_utils.egg-info/top_level.txt