Metadata-Version: 1.0
Name: ryoka-utils
Version: 1.1.55
Summary: Utils for ryoka
Home-page: https://ryoka419319@bitbucket.org/ryoka419319/ryoka_utils.git
Author: Ryoya Kamikawa
Author-email: ry_1324@yahoo.co.jp
License: MIT
Keywords: ryoka utils
Platform: UNKNOWN
